ns3_extended/__init__.py
ns3_extended/write.py
ns3_extended-0.0.9.dist-info/METADATA
ns3_extended-0.0.9.dist-info/WHEEL
ns3_extended-0.0.9.dist-info/licenses/LICENSE
ns3_extended-0.0.9.dist-info/RECORD
